eznf/__init__.py
eznf/block_dec.py
eznf/cardinality.py
eznf/clique.py
eznf/constants.py
eznf/encoder.py
eznf/equivars.py
eznf/es.py
eznf/eznf_parser.py
eznf/maxsat_slp.py
eznf/modeler.py
eznf/order_interval.py
eznf/sem_cnf.py
eznf/signed_uf.py
eznf/solver_output.py
eznf/string_utils.py
eznf/universal_existential_form.py
eznf/utils.py
eznf/xor.py
eznf-0.120.2.dist-info/licenses/LICENSE
eznf-0.120.2.dist-info/METADATA
eznf-0.120.2.dist-info/WHEEL
eznf-0.120.2.dist-info/top_level.txt
eznf-0.120.2.dist-info/RECORD
