Metadata-Version: 2.4
Name: eznf
Version: 0.120.2
Summary: A prototype library to prototype SAT encodings
Author: Bernardo Subercaseaux
Author-email: Bernardo Subercaseaux <bernardosubercaseaux@gmail.com>
Project-URL: Homepage, https://github.com/bsubercaseaux/eznf
Classifier: Programming Language :: Python :: 3
Classifier: License :: OSI Approved :: MIT License
Classifier: Operating System :: OS Independent
Requires-Python: >=3.6
License-File: LICENSE
Requires-Dist: lark
Dynamic: author
Dynamic: license-file
